roboweb_server/__init__.py
roboweb_server/ext.py
roboweb_server/linter legacy.py
roboweb_server/test.py
roboweb_server/static/.last_build_id
roboweb_server/static/debugger.py
roboweb_server/static/deprecated_analyzer.py
roboweb_server/static/favicon.ico
roboweb_server/static/flutter.js
roboweb_server/static/flutter_service_worker.js
roboweb_server/static/index.html
roboweb_server/static/main.dart.js
roboweb_server/static/prompt_eng.py
roboweb_server/static/version.json
roboweb_server/static/assets/AssetManifest.bin
roboweb_server/static/assets/AssetManifest.json
roboweb_server/static/assets/FontManifest.json
roboweb_server/static/assets/NOTICES
roboweb_server/static/assets/assets/jupyter.jpg
roboweb_server/static/assets/assets/oauth2redirect.html
roboweb_server/static/assets/assets/robot-regular.svg
roboweb_server/static/assets/assets/robot-solid.svg
roboweb_server/static/assets/assets/apps/firebase.webp
roboweb_server/static/assets/assets/apps/gcloud.png
roboweb_server/static/assets/assets/apps/github.png
roboweb_server/static/assets/fonts/MaterialIcons-Regular.otf
roboweb_server/static/assets/packages/flutter_signin_button/assets/logos/facebook_new.png
roboweb_server/static/assets/packages/flutter_signin_button/assets/logos/google_dark.png
roboweb_server/static/assets/packages/flutter_signin_button/assets/logos/google_light.png
roboweb_server/static/assets/packages/flutter_signin_button/assets/logos/2.0x/facebook_new.png
roboweb_server/static/assets/packages/flutter_signin_button/assets/logos/2.0x/google_dark.png
roboweb_server/static/assets/packages/flutter_signin_button/assets/logos/2.0x/google_light.png
roboweb_server/static/assets/packages/flutter_signin_button/assets/logos/3.0x/facebook_new.png
roboweb_server/static/assets/packages/flutter_signin_button/assets/logos/3.0x/google_dark.png
roboweb_server/static/assets/packages/flutter_signin_button/assets/logos/3.0x/google_light.png
roboweb_server-0.1.42.dist-info/METADATA
roboweb_server-0.1.42.dist-info/WHEEL
roboweb_server-0.1.42.dist-info/top_level.txt
roboweb_server-0.1.42.dist-info/RECORD
