Metadata-Version: 2.1
Name: roboweb-server
Version: 0.1.42
Summary: ChatGPT plugin for Jupyter Server
Home-page: https://github.com/jlewi/roboweb
Author: Jeremy Lewi
Author-email: jeremy@lewi.us
License: Apache Software License 2.0
Keywords: gpt jupyter-server llm
Platform: UNKNOWN
Classifier: Development Status :: 2 - Pre-Alpha
Classifier: Intended Audience :: Developers
Classifier: Natural Language :: English
Classifier: Programming Language :: Python :: 3.7
Classifier: Programming Language :: Python :: 3.8
Classifier: Programming Language :: Python :: 3.9
Classifier: Programming Language :: Python :: 3.10
Classifier: License :: OSI Approved :: Apache Software License
Requires-Python: >=3.7
Requires-Dist: jupyter
Requires-Dist: pinecone-client
Requires-Dist: python-Levenshtein
Provides-Extra: dev
